framework_determinism-0.1.0.dist-info/DESCRIPTION.rst
framework_determinism-0.1.0.dist-info/METADATA
framework_determinism-0.1.0.dist-info/RECORD
framework_determinism-0.1.0.dist-info/WHEEL
framework_determinism-0.1.0.dist-info/metadata.json
framework_determinism-0.1.0.dist-info/top_level.txt
fwd9m/__init__.py
