Metadata-Version: 2.0
Name: framework-determinism
Version: 0.1.0
Summary: Providing reproducibility in deep learning frameworks
Home-page: https://github.com/NVIDIA/framework-determinism
Author: NVIDIA
Author-email: duncan@nvidia.com
License: Apache 2.0
Platform: UNKNOWN
